[
    {
        "codigo_rue": 71960001,
        "nombre": "Colegio #71960001",
        "departamento": "Santa Cruz",
        "estado": "Activo"
    },
    {
        "codigo_rue": 71960002,
        "nombre": "Colegio #71960002",
        "departamento": "Santa Cruz",
        "estado": "Activo"
    },
    {
        "codigo_rue": 71960003,
        "nombre": "Colegio #71960003",
        "departamento": "Santa Cruz",
        "estado": "Activo"
    },
    {
        "codigo_rue": 71960004,
        "nombre": "Colegio #71960004",
        "departamento": "Santa Cruz",
        "estado": "Activo"
    },
    {
        "codigo_rue": 71960005,
        "nombre": "Colegio #71960005",
        "departamento": "Santa Cruz",
        "estado": "Activo"
    },
    {
        "codigo_rue": 71960006,
        "nombre": "Colegio #71960006",
        "departamento": "Santa Cruz",
        "estado": "Activo"
    },
    {
        "codigo_rue": 71960007,
        "nombre": "Colegio #71960007",
        "departamento": "Santa Cruz",
        "estado": "Activo"
    },
    {
        "codigo_rue": 71960008,
        "nombre": "Colegio #71960008",
        "departamento": "Santa Cruz",
        "estado": "Activo"
    },
    {
        "codigo_rue": 71960009,
        "nombre": "Colegio #71960009",
        "departamento": "Santa Cruz",
        "estado": "Activo"
    },
    {
        "codigo_rue": 71960010,
        "nombre": "Colegio #71960010",
        "departamento": "Santa Cruz",
        "estado": "Activo"
    },
    {
        "codigo_rue": 71960011,
        "nombre": "Colegio #71960011",
        "departamento": "Santa Cruz",
        "estado": "Activo"
    },
    {
        "codigo_rue": 71960012,
        "nombre": "Colegio #71960012",
        "departamento": "Santa Cruz",
        "estado": "Activo"
    },
    {
        "codigo_rue": 71960013,
        "nombre": "Colegio #71960013",
        "departamento": "Santa Cruz",
        "estado": "Activo"
    },
    {
        "codigo_rue": 71960014,
        "nombre": "Colegio #71960014",
        "departamento": "Santa Cruz",
        "estado": "Activo"
    },
    {
        "codigo_rue": 71960015,
        "nombre": "Colegio #71960015",
        "departamento": "Santa Cruz",
        "estado": "Activo"
    },
    {
        "codigo_rue": 71960016,
        "nombre": "Colegio #71960016",
        "departamento": "Santa Cruz",
        "estado": "Activo"
    },
    {
        "codigo_rue": 71960017,
        "nombre": "Colegio #71960017",
        "departamento": "Santa Cruz",
        "estado": "Activo"
    },
    {
        "codigo_rue": 71960018,
        "nombre": "Colegio #71960018",
        "departamento": "Santa Cruz",
        "estado": "Activo"
    },
    {
        "codigo_rue": 71960019,
        "nombre": "Colegio #71960019",
        "departamento": "Santa Cruz",
        "estado": "Activo"
    },
    {
        "codigo_rue": 71960020,
        "nombre": "Colegio #71960020",
        "departamento": "Santa Cruz",
        "estado": "Activo"
    },
    {
        "codigo_rue": 71960021,
        "nombre": "Colegio #71960021",
        "departamento": "Santa Cruz",
        "estado": "Activo"
    },
    {
        "codigo_rue": 71960022,
        "nombre": "Colegio #71960022",
        "departamento": "Santa Cruz",
        "estado": "Activo"
    },
    {
        "codigo_rue": 71960023,
        "nombre": "Colegio #71960023",
        "departamento": "Santa Cruz",
        "estado": "Activo"
    },
    {
        "codigo_rue": 71960024,
        "nombre": "Colegio #71960024",
        "departamento": "Santa Cruz",
        "estado": "Activo"
    },
    {
        "codigo_rue": 71960025,
        "nombre": "Colegio #71960025",
        "departamento": "Santa Cruz",
        "estado": "Activo"
    },
    {
        "codigo_rue": 71960026,
        "nombre": "Colegio #71960026",
        "departamento": "Santa Cruz",
        "estado": "Activo"
    },
    {
        "codigo_rue": 71960027,
        "nombre": "Colegio #71960027",
        "departamento": "Santa Cruz",
        "estado": "Activo"
    },
    {
        "codigo_rue": 71960028,
        "nombre": "Colegio #71960028",
        "departamento": "Santa Cruz",
        "estado": "Activo"
    },
    {
        "codigo_rue": 71960029,
        "nombre": "Colegio #71960029",
        "departamento": "Santa Cruz",
        "estado": "Activo"
    },
    {
        "codigo_rue": 71960030,
        "nombre": "Colegio #71960030",
        "departamento": "Santa Cruz",
        "estado": "Activo"
    },
    {
        "codigo_rue": 71960031,
        "nombre": "Colegio #71960031",
        "departamento": "Santa Cruz",
        "estado": "Activo"
    },
    {
        "codigo_rue": 71960032,
        "nombre": "Colegio #71960032",
        "departamento": "Santa Cruz",
        "estado": "Activo"
    },
    {
        "codigo_rue": 71960033,
        "nombre": "Colegio #71960033",
        "departamento": "Santa Cruz",
        "estado": "Activo"
    },
    {
        "codigo_rue": 71960034,
        "nombre": "Colegio #71960034",
        "departamento": "Santa Cruz",
        "estado": "Activo"
    },
    {
        "codigo_rue": 71960035,
        "nombre": "Colegio #71960035",
        "departamento": "Santa Cruz",
        "estado": "Activo"
    },
    {
        "codigo_rue": 71960036,
        "nombre": "Colegio #71960036",
        "departamento": "Santa Cruz",
        "estado": "Activo"
    },
    {
        "codigo_rue": 71960037,
        "nombre": "Colegio #71960037",
        "departamento": "Santa Cruz",
        "estado": "Activo"
    },
    {
        "codigo_rue": 71960038,
        "nombre": "Colegio #71960038",
        "departamento": "Santa Cruz",
        "estado": "Activo"
    },
    {
        "codigo_rue": 71960039,
        "nombre": "Colegio #71960039",
        "departamento": "Santa Cruz",
        "estado": "Activo"
    },
    {
        "codigo_rue": 71960040,
        "nombre": "Colegio #71960040",
        "departamento": "Santa Cruz",
        "estado": "Activo"
    },
    {
        "codigo_rue": 71960041,
        "nombre": "Colegio #71960041",
        "departamento": "Santa Cruz",
        "estado": "Activo"
    },
    {
        "codigo_rue": 71960042,
        "nombre": "Colegio #71960042",
        "departamento": "Santa Cruz",
        "estado": "Activo"
    },
    {
        "codigo_rue": 71960043,
        "nombre": "Colegio #71960043",
        "departamento": "Santa Cruz",
        "estado": "Activo"
    }
]