[
    {
        "codigo_rue": 81890001,
        "nombre": "Colegio #81890001",
        "departamento": "Santa Cruz",
        "estado": "Activo"
    },
    {
        "codigo_rue": 81890002,
        "nombre": "Colegio #81890002",
        "departamento": "Santa Cruz",
        "estado": "Activo"
    },
    {
        "codigo_rue": 81890003,
        "nombre": "Colegio #81890003",
        "departamento": "Santa Cruz",
        "estado": "Activo"
    },
    {
        "codigo_rue": 81890004,
        "nombre": "Colegio #81890004",
        "departamento": "Santa Cruz",
        "estado": "Activo"
    },
    {
        "codigo_rue": 81890005,
        "nombre": "Colegio #81890005",
        "departamento": "Santa Cruz",
        "estado": "Activo"
    },
    {
        "codigo_rue": 81890006,
        "nombre": "Colegio #81890006",
        "departamento": "Santa Cruz",
        "estado": "Activo"
    },
    {
        "codigo_rue": 81890007,
        "nombre": "Colegio #81890007",
        "departamento": "Santa Cruz",
        "estado": "Activo"
    },
    {
        "codigo_rue": 81890008,
        "nombre": "Colegio #81890008",
        "departamento": "Santa Cruz",
        "estado": "Activo"
    },
    {
        "codigo_rue": 81890009,
        "nombre": "Colegio #81890009",
        "departamento": "Santa Cruz",
        "estado": "Activo"
    },
    {
        "codigo_rue": 81890010,
        "nombre": "Colegio #81890010",
        "departamento": "Santa Cruz",
        "estado": "Activo"
    },
    {
        "codigo_rue": 81890011,
        "nombre": "Colegio #81890011",
        "departamento": "Santa Cruz",
        "estado": "Activo"
    },
    {
        "codigo_rue": 81890012,
        "nombre": "Colegio #81890012",
        "departamento": "Santa Cruz",
        "estado": "Activo"
    },
    {
        "codigo_rue": 81890013,
        "nombre": "Colegio #81890013",
        "departamento": "Santa Cruz",
        "estado": "Activo"
    },
    {
        "codigo_rue": 81890014,
        "nombre": "Colegio #81890014",
        "departamento": "Santa Cruz",
        "estado": "Activo"
    },
    {
        "codigo_rue": 81890015,
        "nombre": "Colegio #81890015",
        "departamento": "Santa Cruz",
        "estado": "Activo"
    },
    {
        "codigo_rue": 81890016,
        "nombre": "Colegio #81890016",
        "departamento": "Santa Cruz",
        "estado": "Activo"
    },
    {
        "codigo_rue": 81890017,
        "nombre": "Colegio #81890017",
        "departamento": "Santa Cruz",
        "estado": "Activo"
    },
    {
        "codigo_rue": 81890018,
        "nombre": "Colegio #81890018",
        "departamento": "Santa Cruz",
        "estado": "Activo"
    },
    {
        "codigo_rue": 81890019,
        "nombre": "Colegio #81890019",
        "departamento": "Santa Cruz",
        "estado": "Activo"
    },
    {
        "codigo_rue": 81890020,
        "nombre": "Colegio #81890020",
        "departamento": "Santa Cruz",
        "estado": "Activo"
    },
    {
        "codigo_rue": 81890021,
        "nombre": "Colegio #81890021",
        "departamento": "Santa Cruz",
        "estado": "Activo"
    },
    {
        "codigo_rue": 81890022,
        "nombre": "Colegio #81890022",
        "departamento": "Santa Cruz",
        "estado": "Activo"
    },
    {
        "codigo_rue": 81890023,
        "nombre": "Colegio #81890023",
        "departamento": "Santa Cruz",
        "estado": "Activo"
    },
    {
        "codigo_rue": 81890024,
        "nombre": "Colegio #81890024",
        "departamento": "Santa Cruz",
        "estado": "Activo"
    },
    {
        "codigo_rue": 81890025,
        "nombre": "Colegio #81890025",
        "departamento": "Santa Cruz",
        "estado": "Activo"
    },
    {
        "codigo_rue": 81890026,
        "nombre": "Colegio #81890026",
        "departamento": "Santa Cruz",
        "estado": "Activo"
    },
    {
        "codigo_rue": 81890027,
        "nombre": "Colegio #81890027",
        "departamento": "Santa Cruz",
        "estado": "Activo"
    },
    {
        "codigo_rue": 81890028,
        "nombre": "Colegio #81890028",
        "departamento": "Santa Cruz",
        "estado": "Activo"
    },
    {
        "codigo_rue": 81890029,
        "nombre": "Colegio #81890029",
        "departamento": "Santa Cruz",
        "estado": "Activo"
    },
    {
        "codigo_rue": 81890030,
        "nombre": "Colegio #81890030",
        "departamento": "Santa Cruz",
        "estado": "Activo"
    },
    {
        "codigo_rue": 81890031,
        "nombre": "Colegio #81890031",
        "departamento": "Santa Cruz",
        "estado": "Activo"
    },
    {
        "codigo_rue": 81890032,
        "nombre": "Colegio #81890032",
        "departamento": "Santa Cruz",
        "estado": "Activo"
    },
    {
        "codigo_rue": 81890033,
        "nombre": "Colegio #81890033",
        "departamento": "Santa Cruz",
        "estado": "Activo"
    },
    {
        "codigo_rue": 81890034,
        "nombre": "Colegio #81890034",
        "departamento": "Santa Cruz",
        "estado": "Activo"
    },
    {
        "codigo_rue": 81890035,
        "nombre": "Colegio #81890035",
        "departamento": "Santa Cruz",
        "estado": "Activo"
    },
    {
        "codigo_rue": 81890036,
        "nombre": "Colegio #81890036",
        "departamento": "Santa Cruz",
        "estado": "Activo"
    },
    {
        "codigo_rue": 81890037,
        "nombre": "Colegio #81890037",
        "departamento": "Santa Cruz",
        "estado": "Activo"
    },
    {
        "codigo_rue": 81890038,
        "nombre": "Colegio #81890038",
        "departamento": "Santa Cruz",
        "estado": "Activo"
    },
    {
        "codigo_rue": 81890039,
        "nombre": "Colegio #81890039",
        "departamento": "Santa Cruz",
        "estado": "Activo"
    },
    {
        "codigo_rue": 81890040,
        "nombre": "Colegio #81890040",
        "departamento": "Santa Cruz",
        "estado": "Activo"
    },
    {
        "codigo_rue": 81890041,
        "nombre": "Colegio #81890041",
        "departamento": "Santa Cruz",
        "estado": "Activo"
    },
    {
        "codigo_rue": 81890042,
        "nombre": "Colegio #81890042",
        "departamento": "Santa Cruz",
        "estado": "Activo"
    },
    {
        "codigo_rue": 81890043,
        "nombre": "Colegio #81890043",
        "departamento": "Santa Cruz",
        "estado": "Activo"
    },
    {
        "codigo_rue": 81890044,
        "nombre": "Colegio #81890044",
        "departamento": "Santa Cruz",
        "estado": "Activo"
    },
    {
        "codigo_rue": 81890045,
        "nombre": "Colegio #81890045",
        "departamento": "Santa Cruz",
        "estado": "Activo"
    },
    {
        "codigo_rue": 81890046,
        "nombre": "Colegio #81890046",
        "departamento": "Santa Cruz",
        "estado": "Activo"
    },
    {
        "codigo_rue": 81890047,
        "nombre": "Colegio #81890047",
        "departamento": "Santa Cruz",
        "estado": "Activo"
    },
    {
        "codigo_rue": 81890048,
        "nombre": "Colegio #81890048",
        "departamento": "Santa Cruz",
        "estado": "Activo"
    },
    {
        "codigo_rue": 81890049,
        "nombre": "Colegio #81890049",
        "departamento": "Santa Cruz",
        "estado": "Activo"
    },
    {
        "codigo_rue": 81890050,
        "nombre": "Colegio #81890050",
        "departamento": "Santa Cruz",
        "estado": "Activo"
    },
    {
        "codigo_rue": 81890051,
        "nombre": "Colegio #81890051",
        "departamento": "Santa Cruz",
        "estado": "Activo"
    },
    {
        "codigo_rue": 81890052,
        "nombre": "Colegio #81890052",
        "departamento": "Santa Cruz",
        "estado": "Activo"
    },
    {
        "codigo_rue": 81890053,
        "nombre": "Colegio #81890053",
        "departamento": "Santa Cruz",
        "estado": "Activo"
    },
    {
        "codigo_rue": 81890054,
        "nombre": "Colegio #81890054",
        "departamento": "Santa Cruz",
        "estado": "Activo"
    },
    {
        "codigo_rue": 81890055,
        "nombre": "Colegio #81890055",
        "departamento": "Santa Cruz",
        "estado": "Activo"
    },
    {
        "codigo_rue": 81890056,
        "nombre": "Colegio #81890056",
        "departamento": "Santa Cruz",
        "estado": "Activo"
    },
    {
        "codigo_rue": 81890057,
        "nombre": "Colegio #81890057",
        "departamento": "Santa Cruz",
        "estado": "Activo"
    },
    {
        "codigo_rue": 81890058,
        "nombre": "Colegio #81890058",
        "departamento": "Santa Cruz",
        "estado": "Activo"
    },
    {
        "codigo_rue": 81890059,
        "nombre": "Colegio #81890059",
        "departamento": "Santa Cruz",
        "estado": "Activo"
    },
    {
        "codigo_rue": 81890060,
        "nombre": "Colegio #81890060",
        "departamento": "Santa Cruz",
        "estado": "Activo"
    },
    {
        "codigo_rue": 81890061,
        "nombre": "Colegio #81890061",
        "departamento": "Santa Cruz",
        "estado": "Activo"
    },
    {
        "codigo_rue": 81890062,
        "nombre": "Colegio #81890062",
        "departamento": "Santa Cruz",
        "estado": "Activo"
    },
    {
        "codigo_rue": 81890063,
        "nombre": "Colegio #81890063",
        "departamento": "Santa Cruz",
        "estado": "Activo"
    },
    {
        "codigo_rue": 81890064,
        "nombre": "Colegio #81890064",
        "departamento": "Santa Cruz",
        "estado": "Activo"
    },
    {
        "codigo_rue": 81890065,
        "nombre": "Colegio #81890065",
        "departamento": "Santa Cruz",
        "estado": "Activo"
    },
    {
        "codigo_rue": 81890066,
        "nombre": "Colegio #81890066",
        "departamento": "Santa Cruz",
        "estado": "Activo"
    },
    {
        "codigo_rue": 81890067,
        "nombre": "Colegio #81890067",
        "departamento": "Santa Cruz",
        "estado": "Activo"
    },
    {
        "codigo_rue": 81890068,
        "nombre": "Colegio #81890068",
        "departamento": "Santa Cruz",
        "estado": "Activo"
    },
    {
        "codigo_rue": 81890069,
        "nombre": "Colegio #81890069",
        "departamento": "Santa Cruz",
        "estado": "Activo"
    },
    {
        "codigo_rue": 81890070,
        "nombre": "Colegio #81890070",
        "departamento": "Santa Cruz",
        "estado": "Activo"
    },
    {
        "codigo_rue": 81890071,
        "nombre": "Colegio #81890071",
        "departamento": "Santa Cruz",
        "estado": "Activo"
    },
    {
        "codigo_rue": 81890072,
        "nombre": "Colegio #81890072",
        "departamento": "Santa Cruz",
        "estado": "Activo"
    },
    {
        "codigo_rue": 81890073,
        "nombre": "Colegio #81890073",
        "departamento": "Santa Cruz",
        "estado": "Activo"
    },
    {
        "codigo_rue": 81890074,
        "nombre": "Colegio #81890074",
        "departamento": "Santa Cruz",
        "estado": "Activo"
    },
    {
        "codigo_rue": 81890075,
        "nombre": "Colegio #81890075",
        "departamento": "Santa Cruz",
        "estado": "Activo"
    },
    {
        "codigo_rue": 81890076,
        "nombre": "Colegio #81890076",
        "departamento": "Santa Cruz",
        "estado": "Activo"
    },
    {
        "codigo_rue": 81890077,
        "nombre": "Colegio #81890077",
        "departamento": "Santa Cruz",
        "estado": "Activo"
    },
    {
        "codigo_rue": 81890078,
        "nombre": "Colegio #81890078",
        "departamento": "Santa Cruz",
        "estado": "Activo"
    },
    {
        "codigo_rue": 81890079,
        "nombre": "Colegio #81890079",
        "departamento": "Santa Cruz",
        "estado": "Activo"
    },
    {
        "codigo_rue": 81890080,
        "nombre": "Colegio #81890080",
        "departamento": "Santa Cruz",
        "estado": "Activo"
    },
    {
        "codigo_rue": 81890081,
        "nombre": "Colegio #81890081",
        "departamento": "Santa Cruz",
        "estado": "Activo"
    },
    {
        "codigo_rue": 81890082,
        "nombre": "Colegio #81890082",
        "departamento": "Santa Cruz",
        "estado": "Activo"
    },
    {
        "codigo_rue": 81890083,
        "nombre": "Colegio #81890083",
        "departamento": "Santa Cruz",
        "estado": "Activo"
    },
    {
        "codigo_rue": 81890084,
        "nombre": "Colegio #81890084",
        "departamento": "Santa Cruz",
        "estado": "Activo"
    },
    {
        "codigo_rue": 81890085,
        "nombre": "Colegio #81890085",
        "departamento": "Santa Cruz",
        "estado": "Activo"
    },
    {
        "codigo_rue": 81890086,
        "nombre": "Colegio #81890086",
        "departamento": "Santa Cruz",
        "estado": "Activo"
    },
    {
        "codigo_rue": 81890087,
        "nombre": "Colegio #81890087",
        "departamento": "Santa Cruz",
        "estado": "Activo"
    },
    {
        "codigo_rue": 81890088,
        "nombre": "Colegio #81890088",
        "departamento": "Santa Cruz",
        "estado": "Activo"
    },
    {
        "codigo_rue": 81890089,
        "nombre": "Colegio #81890089",
        "departamento": "Santa Cruz",
        "estado": "Activo"
    },
    {
        "codigo_rue": 81890090,
        "nombre": "Colegio #81890090",
        "departamento": "Santa Cruz",
        "estado": "Activo"
    },
    {
        "codigo_rue": 81890091,
        "nombre": "Colegio #81890091",
        "departamento": "Santa Cruz",
        "estado": "Activo"
    },
    {
        "codigo_rue": 81890092,
        "nombre": "Colegio #81890092",
        "departamento": "Santa Cruz",
        "estado": "Activo"
    },
    {
        "codigo_rue": 81890093,
        "nombre": "Colegio #81890093",
        "departamento": "Santa Cruz",
        "estado": "Activo"
    },
    {
        "codigo_rue": 81890094,
        "nombre": "Colegio #81890094",
        "departamento": "Santa Cruz",
        "estado": "Activo"
    },
    {
        "codigo_rue": 81890095,
        "nombre": "Colegio #81890095",
        "departamento": "Santa Cruz",
        "estado": "Activo"
    },
    {
        "codigo_rue": 81890096,
        "nombre": "Colegio #81890096",
        "departamento": "Santa Cruz",
        "estado": "Activo"
    },
    {
        "codigo_rue": 81890097,
        "nombre": "Colegio #81890097",
        "departamento": "Santa Cruz",
        "estado": "Activo"
    },
    {
        "codigo_rue": 81890098,
        "nombre": "Colegio #81890098",
        "departamento": "Santa Cruz",
        "estado": "Activo"
    },
    {
        "codigo_rue": 81890099,
        "nombre": "Colegio #81890099",
        "departamento": "Santa Cruz",
        "estado": "Activo"
    },
    {
        "codigo_rue": 81890100,
        "nombre": "Colegio #81890100",
        "departamento": "Santa Cruz",
        "estado": "Activo"
    },
    {
        "codigo_rue": 81890101,
        "nombre": "Colegio #81890101",
        "departamento": "Santa Cruz",
        "estado": "Activo"
    },
    {
        "codigo_rue": 81890102,
        "nombre": "Colegio #81890102",
        "departamento": "Santa Cruz",
        "estado": "Activo"
    },
    {
        "codigo_rue": 81890103,
        "nombre": "Colegio #81890103",
        "departamento": "Santa Cruz",
        "estado": "Activo"
    },
    {
        "codigo_rue": 81890104,
        "nombre": "Colegio #81890104",
        "departamento": "Santa Cruz",
        "estado": "Activo"
    },
    {
        "codigo_rue": 81890105,
        "nombre": "Colegio #81890105",
        "departamento": "Santa Cruz",
        "estado": "Activo"
    },
    {
        "codigo_rue": 81890106,
        "nombre": "Colegio #81890106",
        "departamento": "Santa Cruz",
        "estado": "Activo"
    },
    {
        "codigo_rue": 81890107,
        "nombre": "Colegio #81890107",
        "departamento": "Santa Cruz",
        "estado": "Activo"
    },
    {
        "codigo_rue": 81890108,
        "nombre": "Colegio #81890108",
        "departamento": "Santa Cruz",
        "estado": "Activo"
    },
    {
        "codigo_rue": 81890109,
        "nombre": "Colegio #81890109",
        "departamento": "Santa Cruz",
        "estado": "Activo"
    },
    {
        "codigo_rue": 81890110,
        "nombre": "Colegio #81890110",
        "departamento": "Santa Cruz",
        "estado": "Activo"
    },
    {
        "codigo_rue": 81890111,
        "nombre": "Colegio #81890111",
        "departamento": "Santa Cruz",
        "estado": "Activo"
    },
    {
        "codigo_rue": 81890112,
        "nombre": "Colegio #81890112",
        "departamento": "Santa Cruz",
        "estado": "Activo"
    },
    {
        "codigo_rue": 81890113,
        "nombre": "Colegio #81890113",
        "departamento": "Santa Cruz",
        "estado": "Activo"
    },
    {
        "codigo_rue": 81890114,
        "nombre": "Colegio #81890114",
        "departamento": "Santa Cruz",
        "estado": "Activo"
    },
    {
        "codigo_rue": 81890115,
        "nombre": "Colegio #81890115",
        "departamento": "Santa Cruz",
        "estado": "Activo"
    },
    {
        "codigo_rue": 81890116,
        "nombre": "Colegio #81890116",
        "departamento": "Santa Cruz",
        "estado": "Activo"
    },
    {
        "codigo_rue": 81890117,
        "nombre": "Colegio #81890117",
        "departamento": "Santa Cruz",
        "estado": "Activo"
    },
    {
        "codigo_rue": 81890118,
        "nombre": "Colegio #81890118",
        "departamento": "Santa Cruz",
        "estado": "Activo"
    },
    {
        "codigo_rue": 81890119,
        "nombre": "Colegio #81890119",
        "departamento": "Santa Cruz",
        "estado": "Activo"
    },
    {
        "codigo_rue": 81890120,
        "nombre": "Colegio #81890120",
        "departamento": "Santa Cruz",
        "estado": "Activo"
    },
    {
        "codigo_rue": 81890121,
        "nombre": "Colegio #81890121",
        "departamento": "Santa Cruz",
        "estado": "Activo"
    },
    {
        "codigo_rue": 81890122,
        "nombre": "Colegio #81890122",
        "departamento": "Santa Cruz",
        "estado": "Activo"
    },
    {
        "codigo_rue": 81890123,
        "nombre": "Colegio #81890123",
        "departamento": "Santa Cruz",
        "estado": "Activo"
    },
    {
        "codigo_rue": 81890124,
        "nombre": "Colegio #81890124",
        "departamento": "Santa Cruz",
        "estado": "Activo"
    },
    {
        "codigo_rue": 81890125,
        "nombre": "Colegio #81890125",
        "departamento": "Santa Cruz",
        "estado": "Activo"
    },
    {
        "codigo_rue": 81890126,
        "nombre": "Colegio #81890126",
        "departamento": "Santa Cruz",
        "estado": "Activo"
    },
    {
        "codigo_rue": 81890127,
        "nombre": "Colegio #81890127",
        "departamento": "Santa Cruz",
        "estado": "Activo"
    },
    {
        "codigo_rue": 81890128,
        "nombre": "Colegio #81890128",
        "departamento": "Santa Cruz",
        "estado": "Activo"
    },
    {
        "codigo_rue": 81890129,
        "nombre": "Colegio #81890129",
        "departamento": "Santa Cruz",
        "estado": "Activo"
    },
    {
        "codigo_rue": 81890130,
        "nombre": "Colegio #81890130",
        "departamento": "Santa Cruz",
        "estado": "Activo"
    },
    {
        "codigo_rue": 81890131,
        "nombre": "Colegio #81890131",
        "departamento": "Santa Cruz",
        "estado": "Activo"
    },
    {
        "codigo_rue": 81890132,
        "nombre": "Colegio #81890132",
        "departamento": "Santa Cruz",
        "estado": "Activo"
    },
    {
        "codigo_rue": 81890133,
        "nombre": "Colegio #81890133",
        "departamento": "Santa Cruz",
        "estado": "Activo"
    },
    {
        "codigo_rue": 81890134,
        "nombre": "Colegio #81890134",
        "departamento": "Santa Cruz",
        "estado": "Activo"
    },
    {
        "codigo_rue": 81890135,
        "nombre": "Colegio #81890135",
        "departamento": "Santa Cruz",
        "estado": "Activo"
    },
    {
        "codigo_rue": 81890136,
        "nombre": "Colegio #81890136",
        "departamento": "Santa Cruz",
        "estado": "Activo"
    },
    {
        "codigo_rue": 81890137,
        "nombre": "Colegio #81890137",
        "departamento": "Santa Cruz",
        "estado": "Activo"
    },
    {
        "codigo_rue": 81890138,
        "nombre": "Colegio #81890138",
        "departamento": "Santa Cruz",
        "estado": "Activo"
    },
    {
        "codigo_rue": 81890139,
        "nombre": "Colegio #81890139",
        "departamento": "Santa Cruz",
        "estado": "Activo"
    },
    {
        "codigo_rue": 81890140,
        "nombre": "Colegio #81890140",
        "departamento": "Santa Cruz",
        "estado": "Activo"
    },
    {
        "codigo_rue": 81890141,
        "nombre": "Colegio #81890141",
        "departamento": "Santa Cruz",
        "estado": "Activo"
    },
    {
        "codigo_rue": 81890142,
        "nombre": "Colegio #81890142",
        "departamento": "Santa Cruz",
        "estado": "Activo"
    },
    {
        "codigo_rue": 81890143,
        "nombre": "Colegio #81890143",
        "departamento": "Santa Cruz",
        "estado": "Activo"
    },
    {
        "codigo_rue": 81890144,
        "nombre": "Colegio #81890144",
        "departamento": "Santa Cruz",
        "estado": "Activo"
    },
    {
        "codigo_rue": 81890145,
        "nombre": "Colegio #81890145",
        "departamento": "Santa Cruz",
        "estado": "Activo"
    },
    {
        "codigo_rue": 81890146,
        "nombre": "Colegio #81890146",
        "departamento": "Santa Cruz",
        "estado": "Activo"
    },
    {
        "codigo_rue": 81890147,
        "nombre": "Colegio #81890147",
        "departamento": "Santa Cruz",
        "estado": "Activo"
    },
    {
        "codigo_rue": 81890148,
        "nombre": "Colegio #81890148",
        "departamento": "Santa Cruz",
        "estado": "Activo"
    },
    {
        "codigo_rue": 81890149,
        "nombre": "Colegio #81890149",
        "departamento": "Santa Cruz",
        "estado": "Activo"
    },
    {
        "codigo_rue": 81890150,
        "nombre": "Colegio #81890150",
        "departamento": "Santa Cruz",
        "estado": "Activo"
    }
]